smartfields/__init__.py
smartfields/dependencies.py
smartfields/managers.py
smartfields/models.py
smartfields/settings.py
smartfields/urls.py
smartfields/utils.py
smartfields/views.py
smartfields/crispy/__init__.py
smartfields/crispy/layout.py
smartfields/fields/__init__.py
smartfields/fields/gis.py
smartfields/processors/__init__.py
smartfields/processors/base.py
smartfields/processors/image.py
smartfields/processors/mixin.py
smartfields/processors/text.py
smartfields/processors/video.py
tests/__init__.py
tests/manage.py
tests/settings.py
tests/urls.py
tests/test_app/__init__.py
tests/test_app/forms.py
tests/test_app/models.py
tests/test_app/tests/__init__.py
tests/test_suite/__init__.py
tests/test_suite/test_crispy.py
tests/test_suite/test_fields.py
tests/test_suite/test_files.py
tests/test_suite/test_misc.py
tests/test_suite/test_pre_processing.py
tests/test_suite/test_processors.py
tests/test_suite/test_text.py
tests/test_suite/test_utils.py
tests/test_suite/test_view.py
django_smartfields-1.1.3.dist-info/AUTHORS.rst
django_smartfields-1.1.3.dist-info/LICENSE
django_smartfields-1.1.3.dist-info/METADATA
django_smartfields-1.1.3.dist-info/WHEEL
django_smartfields-1.1.3.dist-info/top_level.txt
django_smartfields-1.1.3.dist-info/RECORD
