Metadata-Version: 1.1
Name: django-smartfields
Version: 1.1.3
Summary: Django Model Fields that are smart.
Home-page: https://github.com/lehins/django-smartfields
Author: Alexey Kuleshevich
Author-email: lehins@yandex.ru
License: MIT License
Keywords: django,model fields,declarative,FileField cleanup,FileField conversion,ImageField conversion,ajax uploading
Platform: any
Classifier: Development Status :: 4 - Beta
Classifier: Framework :: Django
Classifier: Intended Audience :: Developers
Classifier: License :: OSI Approved :: MIT License
Classifier: Natural Language :: English
Classifier: Operating System :: OS Independent
Classifier: Programming Language :: Python
Classifier: Programming Language :: Python :: 2
Classifier: Programming Language :: Python :: 2.7
Classifier: Programming Language :: Python :: 3
Classifier: Programming Language :: Python :: 3.2
Classifier: Programming Language :: Python :: 3.3
Classifier: Programming Language :: Python :: 3.4
Classifier: Programming Language :: Python :: 3.5
Classifier: Programming Language :: Python :: 3.6
Classifier: Programming Language :: Python :: 3.7
Classifier: Programming Language :: Python :: 3.8
Classifier: Topic :: Software Development :: Libraries :: Python Modules
